mylib043/__init__.py
mylib043-0.1.dist-info/LICENSE.txt
mylib043-0.1.dist-info/METADATA
mylib043-0.1.dist-info/WHEEL
mylib043-0.1.dist-info/top_level.txt
mylib043-0.1.dist-info/RECORD
