Metadata-Version: 2.1
Name: mylib043
Version: 0.1
Summary: for calculating square
Home-page: UNKNOWN
Author: Shubham
Author-email: shubham.nagare0777@gmail.com
License: UNKNOWN
Platform: UNKNOWN
Classifier: Programming Language :: Python :: 3
Classifier: License :: OSI Approved :: MIT License
Classifier: Operating System :: OS Independent
